napari_stream/__init__.py
napari_stream/_listener.py
napari_stream/_receiver_widget.py
napari_stream/_utils.py
napari_stream/_version.py
napari_stream/napari.yaml
napari_stream/sender.py
napari_stream-0.1.2.dist-info/licenses/LICENSE
napari_stream-0.1.2.dist-info/METADATA
napari_stream-0.1.2.dist-info/WHEEL
napari_stream-0.1.2.dist-info/entry_points.txt
napari_stream-0.1.2.dist-info/top_level.txt
napari_stream-0.1.2.dist-info/RECORD
